{"schema": ["lcsc", "mfr", "joints", "manufacturer", "description", "datasheet", "price", "images", "url", "attributes"], "components": [["C122895", "LR433T2", 3, "LADDER Elec", "433.92MHz \u00b175kHz 2pF 18\u03a9 SMD SAW Resonators RoHS", "https://datasheet.lcsc.com/lcsc/1810161210_LADDER-Elec-LR433T2_C122895.pdf", [{"qFrom": 5, "qTo": 45, "price": 0.109230769}, {"qFrom": 50, "qTo": 145, "price": 0.083076923}, {"qFrom": 150, "qTo": 495, "price": 0.078307692}, {"qFrom": 500, "qTo": 2495, "price": 0.073538462}, {"qFrom": 2500, "qTo": 4995, "price": 0.071384615}, {"qFrom": 5000, "qTo": 9995, "price": 0.070307692}, {"qFrom": 10000, "qTo": 19995, "price": 0.069538462}, {"qFrom": 20000, "qTo": null, "price": 0.069076923}], null, null, {"Frequency": {"format": "${default}", "primary": "default", "values": {"default": ["433.92MHz", "string"]}}, "Frequency Stability": {"format": "${default}", "primary": "default", "values": {"default": ["-", "string"]}}, "Frequency Tolerance": {"format": "${default}", "primary": "default", "values": {"default": ["\u00b175kHz", "string"]}}, "Operating Temperature": {"format": "${default}", "primary": "default", "values": {"default": ["-40\u2103~+85\u2103", "string"]}}, "Resonant Impedance": {"format": "${default}", "primary": "default", "values": {"default": ["18\u03a9", "string"]}}, "Static Capacitance": {"format": "${default}", "primary": "default", "values": {"default": ["2pF", "string"]}}, "Basic/Extended": {"format": "${default}", "primary": "default", "values": {"default": ["Extended", "string"]}}, "Package": {"format": "${default}", "primary": "default", "values": {"default": ["ANT-SMD", "string"]}}, "Status": {"format": "${default}", "primary": "default", "values": {"default": ["-", "string"]}}}], ["C127904", "LR315T2", 3, "LADDER Elec", "315MHz \u00b175kHz 3.3pF 19\u03a9 SMD SAW Resonators RoHS", "https://datasheet.lcsc.com/lcsc/1811150611_LADDER-Elec-LR315T2_C127904.pdf", [{"qFrom": 5, "qTo": 45, "price": 0.106769231}, {"qFrom": 50, "qTo": 145, "price": 0.080615385}, {"qFrom": 150, "qTo": 495, "price": 0.075846154}, {"qFrom": 500, "qTo": 2495, "price": 0.071076923}, {"qFrom": 2500, "qTo": 4995, "price": 0.068923077}, {"qFrom": 5000, "qTo": 9995, "price": 0.067846154}, {"qFrom": 10000, "qTo": 19995, "price": 0.067076923}, {"qFrom": 20000, "qTo": null, "price": 0.066615385}], null, null, {"Resonant Impedance": {"format": "${default}", "primary": "default", "values": {"default": ["19\u03a9", "string"]}}, "Static Capacitance": {"format": "${default}", "primary": "default", "values": {"default": ["3.3pF", "string"]}}, "Frequency Stability": {"format": "${default}", "primary": "default", "values": {"default": ["-", "string"]}}, "Frequency Tolerance": {"format": "${default}", "primary": "default", "values": {"default": ["\u00b175kHz", "string"]}}, "Operating Temperature": {"format": "${default}", "primary": "default", "values": {"default": ["-40\u2103~+85\u2103", "string"]}}, "Frequency": {"format": "${default}", "primary": "default", "values": {"default": ["315MHz", "string"]}}, "Basic/Extended": {"format": "${default}", "primary": "default", "values": {"default": ["Extended", "string"]}}, "Package": {"format": "${default}", "primary": "default", "values": {"default": ["ANT-SMD", "string"]}}, "Status": {"format": "${default}", "primary": "default", "values": {"default": ["-", "string"]}}}]], "category": "Crystals/Oscillators/Resonators", "subcategory": "SAW Resonators"}