{"schema": ["lcsc", "mfr", "joints", "manufacturer", "description", "datasheet", "price", "images", "url", "attributes"], "components": [["C706736", "AD9914BCPZ", 88, "Analog Devices", "LFCSP-88 Pre-ordered Products RoHS", "", [{"qFrom": 1, "qTo": 9, "price": 693.676923077}, {"qFrom": 10, "qTo": 29, "price": 693.676923077}, {"qFrom": 30, "qTo": 199, "price": 693.676923077}, {"qFrom": 200, "qTo": 499, "price": 268.444615385}, {"qFrom": 500, "qTo": 999, "price": 259.010769231}, {"qFrom": 1000, "qTo": null, "price": 254.349230769}], null, null, {"Basic/Extended": {"format": "${default}", "primary": "default", "values": {"default": ["Extended", "string"]}}, "Package": {"format": "${default}", "primary": "default", "values": {"default": ["LFCSP-88", "string"]}}, "Status": {"format": "${default}", "primary": "default", "values": {"default": ["-", "string"]}}}], ["C579444", "ADXL1004BCPZ", 32, "Analog Devices", "LFCSP-32 Pre-ordered Products RoHS", "", [{"qFrom": 1, "qTo": 9, "price": 140.112307692}, {"qFrom": 10, "qTo": 29, "price": 140.112307692}, {"qFrom": 30, "qTo": 199, "price": 140.112307692}, {"qFrom": 200, "qTo": 499, "price": 54.221538462}, {"qFrom": 500, "qTo": 999, "price": 52.316923077}, {"qFrom": 1000, "qTo": null, "price": 51.375384615}], null, null, {"Basic/Extended": {"format": "${default}", "primary": "default", "values": {"default": ["Extended", "string"]}}, "Package": {"format": "${default}", "primary": "default", "values": {"default": ["LFCSP-32_EP_5.0x5.0x0.5P", "string"]}}, "Status": {"format": "${default}", "primary": "default", "values": {"default": ["-", "string"]}}}], ["C897286", "MC74LCX04DG", 14, "ON Semiconductor", "SOIC-14 Pre-ordered Products RoHS", "", [{"qFrom": 1, "qTo": 9, "price": 0.507692308}, {"qFrom": 10, "qTo": 29, "price": 0.507692308}, {"qFrom": 30, "qTo": 199, "price": 0.507692308}, {"qFrom": 200, "qTo": 499, "price": 0.196923077}, {"qFrom": 500, "qTo": 999, "price": 0.190769231}, {"qFrom": 1000, "qTo": null, "price": 0.186153846}], null, null, {"Basic/Extended": {"format": "${default}", "primary": "default", "values": {"default": ["Extended", "string"]}}, "Package": {"format": "${default}", "primary": "default", "values": {"default": ["SOP-14", "string"]}}, "Status": {"format": "${default}", "primary": "default", "values": {"default": ["-", "string"]}}}], ["C679554", "LTC2220CUP#TRPBF", 64, "Analog Devices", "QFN-64 Pre-ordered Products RoHS", "", [{"qFrom": 1, "qTo": 29, "price": 59.266923077}, {"qFrom": 30, "qTo": null, "price": 58.333538462}], null, null, {"Basic/Extended": {"format": "${default}", "primary": "default", "values": {"default": ["Extended", "string"]}}, "Package": {"format": "${default}", "primary": "default", "values": {"default": ["VQFN-64_EP_9.0x9.0x0.5P", "string"]}}, "Status": {"format": "${default}", "primary": "default", "values": {"default": ["-", "string"]}}}], ["C903445", "AMIS30521C5212RG", 32, "ON Semiconductor", "Pre-ordered Products RoHS", "", [{"qFrom": 1, "qTo": 9, "price": 6.810769231}, {"qFrom": 10, "qTo": 29, "price": 6.810769231}, {"qFrom": 30, "qTo": 199, "price": 6.810769231}, {"qFrom": 200, "qTo": 499, "price": 2.636923077}, {"qFrom": 500, "qTo": 999, "price": 2.543076923}, {"qFrom": 1000, "qTo": null, "price": 2.498461538}], null, null, {"Basic/Extended": {"format": "${default}", "primary": "default", "values": {"default": ["Extended", "string"]}}, "Package": {"format": "${default}", "primary": "default", "values": {"default": ["QFN-32_EP_7.0x7.0x0.65P", "string"]}}, "Status": {"format": "${default}", "primary": "default", "values": {"default": ["-", "string"]}}}], ["C894778", "CM1402-03CP", 10, "ON Semiconductor", "CSP-10 Pre-ordered Products RoHS", "", [{"qFrom": 1, "qTo": 9, "price": 0.472307692}, {"qFrom": 10, "qTo": 29, "price": 0.472307692}, {"qFrom": 30, "qTo": 199, "price": 0.472307692}, {"qFrom": 200, "qTo": 499, "price": 0.183076923}, {"qFrom": 500, "qTo": 999, "price": 0.176923077}, {"qFrom": 1000, "qTo": null, "price": 0.173846154}], null, null, {"Basic/Extended": {"format": "${default}", "primary": "default", "values": {"default": ["Extended", "string"]}}, "Package": {"format": "${default}", "primary": "default", "values": {"default": ["CSP-10_1.33x1.96x0.5P", "string"]}}, "Status": {"format": "${default}", "primary": "default", "values": {"default": ["-", "string"]}}}], ["C898864", "74VHC138M", 16, "ON Semiconductor", "SOIC-16 Pre-ordered Products RoHS", "", [{"qFrom": 1, "qTo": 9, "price": 0.787692308}, {"qFrom": 10, "qTo": 29, "price": 0.787692308}, {"qFrom": 30, "qTo": 199, "price": 0.787692308}, {"qFrom": 200, "qTo": 499, "price": 0.306153846}, {"qFrom": 500, "qTo": 999, "price": 0.295384615}, {"qFrom": 1000, "qTo": null, "price": 0.289230769}], null, null, {"Basic/Extended": {"format": "${default}", "primary": "default", "values": {"default": ["Extended", "string"]}}, "Package": {"format": "${default}", "primary": "default", "values": {"default": ["SOP-16_3.9x9.9x1.27P", "string"]}}, "Status": {"format": "${default}", "primary": "default", "values": {"default": ["-", "string"]}}}], ["C899810", "MOC3042SR2M", 6, "ON Semiconductor", "SMD-DIP-6 Pre-ordered Products RoHS", "", [{"qFrom": 1, "qTo": 9, "price": 1.630769231}, {"qFrom": 10, "qTo": 29, "price": 1.630769231}, {"qFrom": 30, "qTo": 199, "price": 1.630769231}, {"qFrom": 200, "qTo": 499, "price": 0.632307692}, {"qFrom": 500, "qTo": 999, "price": 0.609230769}, {"qFrom": 1000, "qTo": null, "price": 0.598461538}], null, null, {"Basic/Extended": {"format": "${default}", "primary": "default", "values": {"default": ["Extended", "string"]}}, "Package": {"format": "${default}", "primary": "default", "values": {"default": ["DIP_6_6.35x8.5x2.54P", "string"]}}, "Status": {"format": "${default}", "primary": "default", "values": {"default": ["-", "string"]}}}], ["C891972", "NCN5121MNTWG", 40, "ON Semiconductor", "Pre-ordered Products RoHS", "", [{"qFrom": 1, "qTo": 9, "price": 12.063076923}, {"qFrom": 10, "qTo": 29, "price": 12.063076923}, {"qFrom": 30, "qTo": 199, "price": 12.063076923}, {"qFrom": 200, "qTo": 499, "price": 4.669230769}, {"qFrom": 500, "qTo": 999, "price": 4.504615385}, {"qFrom": 1000, "qTo": null, "price": 4.424615385}], null, null, {"Basic/Extended": {"format": "${default}", "primary": "default", "values": {"default": ["Extended", "string"]}}, "Package": {"format": "${default}", "primary": "default", "values": {"default": ["TQFN-40_EP_6.0x6.0x0.5P", "string"]}}, "Status": {"format": "${default}", "primary": "default", "values": {"default": ["-", "string"]}}}], ["C894686", "SZMMSZ5251BT1G", 2, "ON Semiconductor", "SOD-123-2 Pre-ordered Products RoHS", "", [{"qFrom": 1, "qTo": 9, "price": 0.079692308}, {"qFrom": 10, "qTo": 29, "price": 0.079692308}, {"qFrom": 30, "qTo": 199, "price": 0.079692308}, {"qFrom": 200, "qTo": 499, "price": 0.030769231}, {"qFrom": 500, "qTo": 999, "price": 0.029692308}, {"qFrom": 1000, "qTo": null, "price": 0.029230769}], null, null, {"Basic/Extended": {"format": "${default}", "primary": "default", "values": {"default": ["Extended", "string"]}}, "Package": {"format": "${default}", "primary": "default", "values": {"default": ["SOD-123", "string"]}}, "Status": {"format": "${default}", "primary": "default", "values": {"default": ["-", "string"]}}}], ["C891728", "MMSZ5239BT1G", 2, "ON Semiconductor", "SOD-123-2 Pre-ordered Products RoHS", "", [{"qFrom": 10, "qTo": 90, "price": 0.047692308}, {"qFrom": 100, "qTo": 290, "price": 0.035384615}, {"qFrom": 300, "qTo": 990, "price": 0.033230769}, {"qFrom": 1000, "qTo": 4990, "price": 0.030923077}, {"qFrom": 5000, "qTo": 9990, "price": 0.03}, {"qFrom": 10000, "qTo": null, "price": 0.029384615}], null, null, {"Basic/Extended": {"format": "${default}", "primary": "default", "values": {"default": ["Extended", "string"]}}, "Package": {"format": "${default}", "primary": "default", "values": {"default": ["SOD-123", "string"]}}, "Status": {"format": "${default}", "primary": "default", "values": {"default": ["-", "string"]}}}], ["C903861", "MC100EPT20DR2G", 8, "ON Semiconductor", "SOIC-8 Pre-ordered Products RoHS", "", [{"qFrom": 1, "qTo": 9, "price": 9.781538462}, {"qFrom": 10, "qTo": 29, "price": 9.781538462}, {"qFrom": 30, "qTo": 199, "price": 9.781538462}, {"qFrom": 200, "qTo": 499, "price": 3.786153846}, {"qFrom": 500, "qTo": 999, "price": 3.652307692}, {"qFrom": 1000, "qTo": null, "price": 3.587692308}], null, null, {"Basic/Extended": {"format": "${default}", "primary": "default", "values": {"default": ["Extended", "string"]}}, "Package": {"format": "${default}", "primary": "default", "values": {"default": ["SOP-8_3.9x4.9x1.27P", "string"]}}, "Status": {"format": "${default}", "primary": "default", "values": {"default": ["-", "string"]}}}], ["C903863", "MC100EPT21DR2G", 8, "ON Semiconductor", "SOIC-8 Pre-ordered Products RoHS", "", [{"qFrom": 1, "qTo": 9, "price": 9.781538462}, {"qFrom": 10, "qTo": 29, "price": 9.781538462}, {"qFrom": 30, "qTo": 199, "price": 9.781538462}, {"qFrom": 200, "qTo": 499, "price": 3.786153846}, {"qFrom": 500, "qTo": 999, "price": 3.652307692}, {"qFrom": 1000, "qTo": null, "price": 3.587692308}], null, null, {"Basic/Extended": {"format": "${default}", "primary": "default", "values": {"default": ["Extended", "string"]}}, "Package": {"format": "${default}", "primary": "default", "values": {"default": ["SOP-8_3.9x4.9x1.27P", "string"]}}, "Status": {"format": "${default}", "primary": "default", "values": {"default": ["-", "string"]}}}], ["C578299", "AD5791BRUZ", 20, "Analog Devices", "TSSOP-20 Pre-ordered Products RoHS", "", [{"qFrom": 1, "qTo": 9, "price": 111.326153846}, {"qFrom": 10, "qTo": 29, "price": 96.1}, {"qFrom": 30, "qTo": 99, "price": 93.304615385}, {"qFrom": 100, "qTo": 499, "price": 90.507692308}, {"qFrom": 500, "qTo": 999, "price": 89.264615385}, {"qFrom": 1000, "qTo": null, "price": 87.729230769}], null, null, {"Basic/Extended": {"format": "${default}", "primary": "default", "values": {"default": ["Extended", "string"]}}, "Package": {"format": "${default}", "primary": "default", "values": {"default": ["TSSOP-20_4.4x6.5x0.65P", "string"]}}, "Status": {"format": "${default}", "primary": "default", "values": {"default": ["-", "string"]}}}], ["C894313", "SHN1B01FDW1T1G", 6, "ON Semiconductor", "SC-74-6 Pre-ordered Products RoHS", "", [{"qFrom": 1, "qTo": 9, "price": 0.078615385}, {"qFrom": 10, "qTo": 29, "price": 0.078615385}, {"qFrom": 30, "qTo": 199, "price": 0.078615385}, {"qFrom": 200, "qTo": 499, "price": 0.030461538}, {"qFrom": 500, "qTo": 999, "price": 0.029384615}, {"qFrom": 1000, "qTo": null, "price": 0.028769231}], null, null, {"Basic/Extended": {"format": "${default}", "primary": "default", "values": {"default": ["Extended", "string"]}}, "Package": {"format": "${default}", "primary": "default", "values": {"default": ["SC-74-6", "string"]}}, "Status": {"format": "${default}", "primary": "default", "values": {"default": ["-", "string"]}}}], ["C962091", "MAX1978ETM+T", 48, "Maxim Integrated", "TQFN-48 Pre-ordered Products RoHS", "", [{"qFrom": 1, "qTo": 9, "price": 11.678461538}, {"qFrom": 10, "qTo": 29, "price": 10.115384615}, {"qFrom": 30, "qTo": 99, "price": 9.827692308}, {"qFrom": 100, "qTo": 499, "price": 9.54}, {"qFrom": 500, "qTo": 999, "price": 9.412307692}, {"qFrom": 1000, "qTo": null, "price": 9.255384615}], null, null, {"Basic/Extended": {"format": "${default}", "primary": "default", "values": {"default": ["Extended", "string"]}}, "Package": {"format": "${default}", "primary": "default", "values": {"default": ["PQFN-48_EP_7.0x7.0x0.5P", "string"]}}, "Status": {"format": "${default}", "primary": "default", "values": {"default": ["-", "string"]}}}], ["C915968", "STM32L072RBT6", 64, "STMicroelectronics", "LQFP-64 Pre-ordered Products RoHS", "", [{"qFrom": 1, "qTo": 9, "price": 3.418461538}, {"qFrom": 10, "qTo": 29, "price": 2.941538462}, {"qFrom": 30, "qTo": 99, "price": 2.853846154}, {"qFrom": 100, "qTo": 499, "price": 2.766153846}, {"qFrom": 500, "qTo": 999, "price": 2.727692308}, {"qFrom": 1000, "qTo": null, "price": 2.68}], null, null, {"Basic/Extended": {"format": "${default}", "primary": "default", "values": {"default": ["Extended", "string"]}}, "Package": {"format": "${default}", "primary": "default", "values": {"default": ["LQFP-64_10.0x10.0x0.5P", "string"]}}, "Status": {"format": "${default}", "primary": "default", "values": {"default": ["-", "string"]}}}], ["C1986354", "XRCGB25M000F1H00R0", 4, "Murata Electronics", "SMD-4 Pre-ordered Products RoHS", "", [{"qFrom": 1, "qTo": 9, "price": 0.350153846}, {"qFrom": 10, "qTo": 29, "price": 0.350153846}, {"qFrom": 30, "qTo": 199, "price": 0.350153846}, {"qFrom": 200, "qTo": 499, "price": 0.135538462}, {"qFrom": 500, "qTo": 999, "price": 0.130769231}, {"qFrom": 1000, "qTo": null, "price": 0.128461538}], null, null, {"Basic/Extended": {"format": "${default}", "primary": "default", "values": {"default": ["Extended", "string"]}}, "Package": {"format": "${default}", "primary": "default", "values": {"default": ["SMD-CRY_1.6x2.0_4P", "string"]}}, "Status": {"format": "${default}", "primary": "default", "values": {"default": ["-", "string"]}}}], ["C2450445", "7B-20.000MEEQ-T", 4, "TXC Corp", "SMD-4 Pre-ordered Products RoHS", "", [{"qFrom": 1, "qTo": 9, "price": 0.586153846}, {"qFrom": 10, "qTo": 29, "price": 0.430769231}, {"qFrom": 30, "qTo": 99, "price": 0.403076923}, {"qFrom": 100, "qTo": 499, "price": 0.373846154}, {"qFrom": 500, "qTo": 999, "price": 0.361538462}, {"qFrom": 1000, "qTo": null, "price": 0.355384615}], null, null, {"Basic/Extended": {"format": "${default}", "primary": "default", "values": {"default": ["Extended", "string"]}}, "Package": {"format": "${default}", "primary": "default", "values": {"default": ["SMD-CRY-3.2x5.0x4P", "string"]}}, "Status": {"format": "${default}", "primary": "default", "values": {"default": ["-", "string"]}}}], ["C653621", "AD9613BCPZ-170", 64, "Analog Devices", "LFCSP-64 Pre-ordered Products RoHS", "", [{"qFrom": 1, "qTo": 9, "price": 146.626153846}, {"qFrom": 10, "qTo": 29, "price": 146.626153846}, {"qFrom": 30, "qTo": 199, "price": 146.626153846}, {"qFrom": 200, "qTo": 499, "price": 56.743076923}, {"qFrom": 500, "qTo": 999, "price": 54.747692308}, {"qFrom": 1000, "qTo": null, "price": 53.763076923}], null, null, {"Basic/Extended": {"format": "${default}", "primary": "default", "values": {"default": ["Extended", "string"]}}, "Package": {"format": "${default}", "primary": "default", "values": {"default": ["LFCSP-64_EP_9.0x9.0x0.5P", "string"]}}, "Status": {"format": "${default}", "primary": "default", "values": {"default": ["-", "string"]}}}], ["C2598551", "7R-27.120MAAQ-T", 4, "TXC Corp", "SMD-4 Pre-ordered Products RoHS", "", [{"qFrom": 1, "qTo": 9, "price": 0.304615385}, {"qFrom": 10, "qTo": 29, "price": 0.224615385}, {"qFrom": 30, "qTo": 99, "price": 0.209230769}, {"qFrom": 100, "qTo": 499, "price": 0.193846154}, {"qFrom": 500, "qTo": 999, "price": 0.187692308}, {"qFrom": 1000, "qTo": null, "price": 0.184615385}], null, null, {"Basic/Extended": {"format": "${default}", "primary": "default", "values": {"default": ["Extended", "string"]}}, "Package": {"format": "${default}", "primary": "default", "values": {"default": ["SMD-CRY-1.65x2.0_4P", "string"]}}, "Status": {"format": "${default}", "primary": "default", "values": {"default": ["-", "string"]}}}], ["C897043", "MC34167TG", 5, "ON Semiconductor", "TO-220-5 Pre-ordered Products RoHS", "", [{"qFrom": 1, "qTo": 9, "price": 5.144615385}, {"qFrom": 10, "qTo": 29, "price": 5.144615385}, {"qFrom": 30, "qTo": 199, "price": 5.144615385}, {"qFrom": 200, "qTo": 499, "price": 1.990769231}, {"qFrom": 500, "qTo": 999, "price": 1.921538462}, {"qFrom": 1000, "qTo": null, "price": 1.886153846}], null, null, {"Basic/Extended": {"format": "${default}", "primary": "default", "values": {"default": ["Extended", "string"]}}, "Package": {"format": "${default}", "primary": "default", "values": {"default": ["SIP-5_4.46x10.22x1.702P", "string"]}}, "Status": {"format": "${default}", "primary": "default", "values": {"default": ["-", "string"]}}}], ["C1677419", "SG-8002JA 1.0000M-PCMB ROHS", 4, "Seiko Epson", "SOJ-4 Pre-ordered Products RoHS", "", [{"qFrom": 1, "qTo": 9, "price": 2.426153846}, {"qFrom": 10, "qTo": 29, "price": 2.426153846}, {"qFrom": 30, "qTo": 199, "price": 2.426153846}, {"qFrom": 200, "qTo": 499, "price": 0.94}, {"qFrom": 500, "qTo": 999, "price": 0.906153846}, {"qFrom": 1000, "qTo": null, "price": 0.890769231}], null, null, {"Basic/Extended": {"format": "${default}", "primary": "default", "values": {"default": ["Extended", "string"]}}, "Package": {"format": "${default}", "primary": "default", "values": {"default": ["SMD-4_8.65X14.0X5.08P", "string"]}}, "Status": {"format": "${default}", "primary": "default", "values": {"default": ["-", "string"]}}}], ["C897665", "MM74HC86MTC", 14, "ON Semiconductor", "TSSOP-14 Pre-ordered Products RoHS", "", [{"qFrom": 1, "qTo": 9, "price": 0.358307692}, {"qFrom": 10, "qTo": 29, "price": 0.358307692}, {"qFrom": 30, "qTo": 199, "price": 0.358307692}, {"qFrom": 200, "qTo": 499, "price": 0.138615385}, {"qFrom": 500, "qTo": 999, "price": 0.133846154}, {"qFrom": 1000, "qTo": null, "price": 0.131384615}], null, null, {"Basic/Extended": {"format": "${default}", "primary": "default", "values": {"default": ["Extended", "string"]}}, "Package": {"format": "${default}", "primary": "default", "values": {"default": ["TSSOP-14", "string"]}}, "Status": {"format": "${default}", "primary": "default", "values": {"default": ["-", "string"]}}}], ["C899258", "FOD3180S", 8, "ON Semiconductor", "SMD-8 Pre-ordered Products RoHS", "", [{"qFrom": 1, "qTo": 9, "price": 2.898461538}, {"qFrom": 10, "qTo": 29, "price": 2.898461538}, {"qFrom": 30, "qTo": 199, "price": 2.898461538}, {"qFrom": 200, "qTo": 499, "price": 1.121538462}, {"qFrom": 500, "qTo": 999, "price": 1.083076923}, {"qFrom": 1000, "qTo": null, "price": 1.063076923}], null, null, {"Basic/Extended": {"format": "${default}", "primary": "default", "values": {"default": ["Extended", "string"]}}, "Package": {"format": "${default}", "primary": "default", "values": {"default": ["SMD-8", "string"]}}, "Status": {"format": "${default}", "primary": "default", "values": {"default": ["-", "string"]}}}], ["C903510", "FAN3278TMX", 8, "ON Semiconductor", "SOIC-8 Pre-ordered Products RoHS", "", [{"qFrom": 1, "qTo": 9, "price": 1.413846154}, {"qFrom": 10, "qTo": 29, "price": 1.413846154}, {"qFrom": 30, "qTo": 199, "price": 1.413846154}, {"qFrom": 200, "qTo": 499, "price": 0.547692308}, {"qFrom": 500, "qTo": 999, "price": 0.527692308}, {"qFrom": 1000, "qTo": null, "price": 0.518461538}], null, null, {"Basic/Extended": {"format": "${default}", "primary": "default", "values": {"default": ["Extended", "string"]}}, "Package": {"format": "${default}", "primary": "default", "values": {"default": ["SOIC-8", "string"]}}, "Status": {"format": "${default}", "primary": "default", "values": {"default": ["-", "string"]}}}], ["C891656", "MM5Z3V3T1G", 2, "ON Semiconductor", "SOD-523 Pre-ordered Products RoHS", "", [{"qFrom": 1, "qTo": 9, "price": 0.070615385}, {"qFrom": 10, "qTo": 29, "price": 0.070615385}, {"qFrom": 30, "qTo": 199, "price": 0.070615385}, {"qFrom": 200, "qTo": 499, "price": 0.027384615}, {"qFrom": 500, "qTo": 999, "price": 0.026307692}, {"qFrom": 1000, "qTo": null, "price": 0.025846154}], null, null, {"Basic/Extended": {"format": "${default}", "primary": "default", "values": {"default": ["Extended", "string"]}}, "Package": {"format": "${default}", "primary": "default", "values": {"default": ["SOD-523", "string"]}}, "Status": {"format": "${default}", "primary": "default", "values": {"default": ["-", "string"]}}}], ["C898446", "2SB1216S-TL-E", 3, "ON Semiconductor", "TO-252-3 Pre-ordered Products RoHS", "", [{"qFrom": 1, "qTo": 9, "price": 0.763076923}, {"qFrom": 10, "qTo": 29, "price": 0.763076923}, {"qFrom": 30, "qTo": 199, "price": 0.763076923}, {"qFrom": 200, "qTo": 499, "price": 0.295384615}, {"qFrom": 500, "qTo": 999, "price": 0.286153846}, {"qFrom": 1000, "qTo": null, "price": 0.28}], null, null, {"Basic/Extended": {"format": "${default}", "primary": "default", "values": {"default": ["Extended", "string"]}}, "Package": {"format": "${default}", "primary": "default", "values": {"default": ["TO-252-3", "string"]}}, "Status": {"format": "${default}", "primary": "default", "values": {"default": ["-", "string"]}}}], ["C578854", "AD9627ABCPZ-150", 64, "Analog Devices", "LFCSP-64 Pre-ordered Products RoHS", "", [{"qFrom": 1, "qTo": 9, "price": 190.464615385}, {"qFrom": 10, "qTo": 29, "price": 190.464615385}, {"qFrom": 30, "qTo": 199, "price": 190.464615385}, {"qFrom": 200, "qTo": 499, "price": 73.707692308}, {"qFrom": 500, "qTo": 999, "price": 71.116923077}, {"qFrom": 1000, "qTo": null, "price": 69.836923077}], null, null, {"Basic/Extended": {"format": "${default}", "primary": "default", "values": {"default": ["Extended", "string"]}}, "Package": {"format": "${default}", "primary": "default", "values": {"default": ["LFCSP-64", "string"]}}, "Status": {"format": "${default}", "primary": "default", "values": {"default": ["-", "string"]}}}], ["C1677385", "SG3225VAN 133.2620M-KJGAB", 6, "Seiko Epson", "SMD-6 Pre-ordered Products RoHS", "", [{"qFrom": 1, "qTo": 9, "price": 2.401538462}, {"qFrom": 10, "qTo": 29, "price": 2.401538462}, {"qFrom": 30, "qTo": 199, "price": 2.401538462}, {"qFrom": 200, "qTo": 499, "price": 0.930769231}, {"qFrom": 500, "qTo": 999, "price": 0.896923077}, {"qFrom": 1000, "qTo": null, "price": 0.881538462}], null, null, {"Basic/Extended": {"format": "${default}", "primary": "default", "values": {"default": ["Extended", "string"]}}, "Package": {"format": "${default}", "primary": "default", "values": {"default": ["SMD-6", "string"]}}, "Status": {"format": "${default}", "primary": "default", "values": {"default": ["-", "string"]}}}], ["C1677390", "SG3225VAN 312.5000M-KEGAB", 6, "Seiko Epson", "SMD-6 Pre-ordered Products RoHS", "", [{"qFrom": 1, "qTo": 9, "price": 2.401538462}, {"qFrom": 10, "qTo": 29, "price": 2.401538462}, {"qFrom": 30, "qTo": 199, "price": 2.401538462}, {"qFrom": 200, "qTo": 499, "price": 0.930769231}, {"qFrom": 500, "qTo": 999, "price": 0.896923077}, {"qFrom": 1000, "qTo": null, "price": 0.881538462}], null, null, {"Basic/Extended": {"format": "${default}", "primary": "default", "values": {"default": ["Extended", "string"]}}, "Package": {"format": "${default}", "primary": "default", "values": {"default": ["SMD-6", "string"]}}, "Status": {"format": "${default}", "primary": "default", "values": {"default": ["-", "string"]}}}], ["C1996467", "SG3225VAN 312.5000M-KEGA6", 6, "Seiko Epson", "SMD-6 Pre-ordered Products RoHS", "", [{"qFrom": 1, "qTo": 9, "price": 2.46}, {"qFrom": 10, "qTo": 29, "price": 2.46}, {"qFrom": 30, "qTo": 199, "price": 2.46}, {"qFrom": 200, "qTo": 499, "price": 0.952307692}, {"qFrom": 500, "qTo": 999, "price": 0.918461538}, {"qFrom": 1000, "qTo": null, "price": 0.903076923}], null, null, {"Basic/Extended": {"format": "${default}", "primary": "default", "values": {"default": ["Extended", "string"]}}, "Package": {"format": "${default}", "primary": "default", "values": {"default": ["SMD-6", "string"]}}, "Status": {"format": "${default}", "primary": "default", "values": {"default": ["-", "string"]}}}], ["C1677383", "SG3225VAN 148.3500M-KJGAB", 6, "Seiko Epson", "SMD-6 Pre-ordered Products RoHS", "", [{"qFrom": 1, "qTo": 9, "price": 2.401538462}, {"qFrom": 10, "qTo": 29, "price": 2.401538462}, {"qFrom": 30, "qTo": 199, "price": 2.401538462}, {"qFrom": 200, "qTo": 499, "price": 0.930769231}, {"qFrom": 500, "qTo": 999, "price": 0.896923077}, {"qFrom": 1000, "qTo": null, "price": 0.881538462}], null, null, {"Basic/Extended": {"format": "${default}", "primary": "default", "values": {"default": ["Extended", "string"]}}, "Package": {"format": "${default}", "primary": "default", "values": {"default": ["SMD-6", "string"]}}, "Status": {"format": "${default}", "primary": "default", "values": {"default": ["-", "string"]}}}], ["C1677386", "SG3225VAN 100.000000M-KJBAB", 6, "Seiko Epson", "SMD-6 Pre-ordered Products RoHS", "", [{"qFrom": 1, "qTo": 9, "price": 2.401538462}, {"qFrom": 10, "qTo": 29, "price": 2.401538462}, {"qFrom": 30, "qTo": 199, "price": 2.401538462}, {"qFrom": 200, "qTo": 499, "price": 0.930769231}, {"qFrom": 500, "qTo": 999, "price": 0.896923077}, {"qFrom": 1000, "qTo": null, "price": 0.881538462}], null, null, {"Basic/Extended": {"format": "${default}", "primary": "default", "values": {"default": ["Extended", "string"]}}, "Package": {"format": "${default}", "primary": "default", "values": {"default": ["SMD-6", "string"]}}, "Status": {"format": "${default}", "primary": "default", "values": {"default": ["-", "string"]}}}], ["C1988534", "ASTX-H11-20.000MHZ-T", 4, "Abracon LLC", "SMD-4 Pre-ordered Products RoHS", "", [{"qFrom": 1, "qTo": 9, "price": 3.543076923}, {"qFrom": 10, "qTo": 29, "price": 3.543076923}, {"qFrom": 30, "qTo": 199, "price": 3.543076923}, {"qFrom": 200, "qTo": 499, "price": 1.370769231}, {"qFrom": 500, "qTo": 999, "price": 1.323076923}, {"qFrom": 1000, "qTo": null, "price": 1.3}], null, null, {"Basic/Extended": {"format": "${default}", "primary": "default", "values": {"default": ["Extended", "string"]}}, "Package": {"format": "${default}", "primary": "default", "values": {"default": ["SMD-4", "string"]}}, "Status": {"format": "${default}", "primary": "default", "values": {"default": ["-", "string"]}}}], ["C893251", "NCV8606MN33T2G", 6, "ON Semiconductor", "DFN-6 Pre-ordered Products RoHS", "", [{"qFrom": 1, "qTo": 9, "price": 1.558461538}, {"qFrom": 10, "qTo": 29, "price": 1.558461538}, {"qFrom": 30, "qTo": 199, "price": 1.558461538}, {"qFrom": 200, "qTo": 499, "price": 0.603076923}, {"qFrom": 500, "qTo": 999, "price": 0.583076923}, {"qFrom": 1000, "qTo": null, "price": 0.572307692}], null, null, {"Basic/Extended": {"format": "${default}", "primary": "default", "values": {"default": ["Extended", "string"]}}, "Package": {"format": "${default}", "primary": "default", "values": {"default": ["DFN-6", "string"]}}, "Status": {"format": "${default}", "primary": "default", "values": {"default": ["-", "string"]}}}], ["C1988535", "ASE-25.000MHZ-ET", 4, "Abracon LLC", "SMD-4 Pre-ordered Products RoHS", "", [{"qFrom": 1, "qTo": 9, "price": 1.373846154}, {"qFrom": 10, "qTo": 29, "price": 1.373846154}, {"qFrom": 30, "qTo": 199, "price": 1.373846154}, {"qFrom": 200, "qTo": 499, "price": 0.532307692}, {"qFrom": 500, "qTo": 999, "price": 0.513846154}, {"qFrom": 1000, "qTo": null, "price": 0.504615385}], null, null, {"Basic/Extended": {"format": "${default}", "primary": "default", "values": {"default": ["Extended", "string"]}}, "Package": {"format": "${default}", "primary": "default", "values": {"default": ["SMD-4", "string"]}}, "Status": {"format": "${default}", "primary": "default", "values": {"default": ["-", "string"]}}}], ["C913221", "TBU-CA065-200-WH", 3, "BOURNS", "SMT Pre-ordered Products RoHS", "", [{"qFrom": 1, "qTo": 9, "price": 2.404615385}, {"qFrom": 10, "qTo": 29, "price": 2.404615385}, {"qFrom": 30, "qTo": 199, "price": 2.404615385}, {"qFrom": 200, "qTo": 499, "price": 0.930769231}, {"qFrom": 500, "qTo": 999, "price": 0.898461538}, {"qFrom": 1000, "qTo": null, "price": 0.883076923}], null, null, {"Basic/Extended": {"format": "${default}", "primary": "default", "values": {"default": ["Extended", "string"]}}, "Package": {"format": "${default}", "primary": "default", "values": {"default": ["SMT", "string"]}}, "Status": {"format": "${default}", "primary": "default", "values": {"default": ["-", "string"]}}}], ["C1987198", "ASEMB-8.000MHZ-XY-T", 4, "Abracon LLC", "SMD-4 Pre-ordered Products RoHS", "", [{"qFrom": 1, "qTo": 9, "price": 2.455384615}, {"qFrom": 10, "qTo": 29, "price": 2.455384615}, {"qFrom": 30, "qTo": 199, "price": 2.455384615}, {"qFrom": 200, "qTo": 499, "price": 0.950769231}, {"qFrom": 500, "qTo": 999, "price": 0.916923077}, {"qFrom": 1000, "qTo": null, "price": 0.901538462}], null, null, {"Basic/Extended": {"format": "${default}", "primary": "default", "values": {"default": ["Extended", "string"]}}, "Package": {"format": "${default}", "primary": "default", "values": {"default": ["SMD-4", "string"]}}, "Status": {"format": "${default}", "primary": "default", "values": {"default": ["-", "string"]}}}], ["C892394", "NCP305LSQ25T1G", 4, "ON Semiconductor", "SC-82AB-4 Pre-ordered Products RoHS", "", [{"qFrom": 1, "qTo": 9, "price": 0.434769231}, {"qFrom": 10, "qTo": 29, "price": 0.434769231}, {"qFrom": 30, "qTo": 199, "price": 0.434769231}, {"qFrom": 200, "qTo": 499, "price": 0.168230769}, {"qFrom": 500, "qTo": 999, "price": 0.162323077}, {"qFrom": 1000, "qTo": null, "price": 0.1594}], null, null, {"Basic/Extended": {"format": "${default}", "primary": "default", "values": {"default": ["Extended", "string"]}}, "Package": {"format": "${default}", "primary": "default", "values": {"default": ["SC-82AB-4", "string"]}}, "Status": {"format": "${default}", "primary": "default", "values": {"default": ["-", "string"]}}}], ["C578462", "AD7677ASTZ", 48, "Analog Devices", "LQFP-48 Pre-ordered Products RoHS", "", [{"qFrom": 1, "qTo": 9, "price": 151.947692308}, {"qFrom": 10, "qTo": 29, "price": 151.947692308}, {"qFrom": 30, "qTo": 199, "price": 151.947692308}, {"qFrom": 200, "qTo": 499, "price": 58.801538462}, {"qFrom": 500, "qTo": 999, "price": 56.735384615}, {"qFrom": 1000, "qTo": null, "price": 55.713846154}], null, null, {"Basic/Extended": {"format": "${default}", "primary": "default", "values": {"default": ["Extended", "string"]}}, "Package": {"format": "${default}", "primary": "default", "values": {"default": ["LQFP-48", "string"]}}, "Status": {"format": "${default}", "primary": "default", "values": {"default": ["-", "string"]}}}], ["C900643", "74LVTH244MTC", 20, "ON Semiconductor", "TSSOP-20 Pre-ordered Products RoHS", "", [{"qFrom": 1, "qTo": 9, "price": 0.841538462}, {"qFrom": 10, "qTo": 29, "price": 0.841538462}, {"qFrom": 30, "qTo": 199, "price": 0.841538462}, {"qFrom": 200, "qTo": 499, "price": 0.326153846}, {"qFrom": 500, "qTo": 999, "price": 0.313846154}, {"qFrom": 1000, "qTo": null, "price": 0.309230769}], null, null, {"Basic/Extended": {"format": "${default}", "primary": "default", "values": {"default": ["Extended", "string"]}}, "Package": {"format": "${default}", "primary": "default", "values": {"default": ["TSSOP-20", "string"]}}, "Status": {"format": "${default}", "primary": "default", "values": {"default": ["-", "string"]}}}], ["C2450536", "ECS-120-10-36B-CWY-TR", 4, "ECS", "SMD-4 Pre-ordered Products RoHS", "", [{"qFrom": 1, "qTo": 9, "price": 0.349076923}, {"qFrom": 10, "qTo": 29, "price": 0.349076923}, {"qFrom": 30, "qTo": 199, "price": 0.349076923}, {"qFrom": 200, "qTo": 499, "price": 0.135076923}, {"qFrom": 500, "qTo": 999, "price": 0.130307692}, {"qFrom": 1000, "qTo": null, "price": 0.128}], null, null, {"Basic/Extended": {"format": "${default}", "primary": "default", "values": {"default": ["Extended", "string"]}}, "Package": {"format": "${default}", "primary": "default", "values": {"default": ["SMD-4", "string"]}}, "Status": {"format": "${default}", "primary": "default", "values": {"default": ["-", "string"]}}}], ["C891633", "MM3Z5V1C", 2, "ON Semiconductor", "SOD-323F-2 Pre-ordered Products RoHS", "", [{"qFrom": 1, "qTo": 9, "price": 0.055076923}, {"qFrom": 10, "qTo": 29, "price": 0.055076923}, {"qFrom": 30, "qTo": 199, "price": 0.055076923}, {"qFrom": 200, "qTo": 499, "price": 0.021384615}, {"qFrom": 500, "qTo": 999, "price": 0.020615385}, {"qFrom": 1000, "qTo": null, "price": 0.020153846}], null, null, {"Basic/Extended": {"format": "${default}", "primary": "default", "values": {"default": ["Extended", "string"]}}, "Package": {"format": "${default}", "primary": "default", "values": {"default": ["SOD-323F-2", "string"]}}, "Status": {"format": "${default}", "primary": "default", "values": {"default": ["-", "string"]}}}], ["C653363", "AD9246BCPZRL7-105", 48, "Analog Devices", "LFCSP-48 Pre-ordered Products RoHS", "", [{"qFrom": 1, "qTo": 9, "price": 158.607692308}, {"qFrom": 10, "qTo": 29, "price": 158.607692308}, {"qFrom": 30, "qTo": 199, "price": 158.607692308}, {"qFrom": 200, "qTo": 499, "price": 61.38}, {"qFrom": 500, "qTo": 999, "price": 59.223076923}, {"qFrom": 1000, "qTo": null, "price": 58.156923077}], null, null, {"Basic/Extended": {"format": "${default}", "primary": "default", "values": {"default": ["Extended", "string"]}}, "Package": {"format": "${default}", "primary": "default", "values": {"default": ["LFCSP-48", "string"]}}, "Status": {"format": "${default}", "primary": "default", "values": {"default": ["-", "string"]}}}], ["C653361", "AD9246BCPZ-105", 48, "Analog Devices", "LFCSP-48 Pre-ordered Products RoHS", "", [{"qFrom": 1, "qTo": 9, "price": 158.607692308}, {"qFrom": 10, "qTo": 29, "price": 158.607692308}, {"qFrom": 30, "qTo": 199, "price": 158.607692308}, {"qFrom": 200, "qTo": 499, "price": 61.38}, {"qFrom": 500, "qTo": 999, "price": 59.223076923}, {"qFrom": 1000, "qTo": null, "price": 58.156923077}], null, null, {"Basic/Extended": {"format": "${default}", "primary": "default", "values": {"default": ["Extended", "string"]}}, "Package": {"format": "${default}", "primary": "default", "values": {"default": ["LFCSP-48", "string"]}}, "Status": {"format": "${default}", "primary": "default", "values": {"default": ["-", "string"]}}}], ["C578828", "AD9246BCPZ-125", 48, "Analog Devices", "LFCSP-48 Pre-ordered Products RoHS", "", [{"qFrom": 1, "qTo": 9, "price": 192.547692308}, {"qFrom": 10, "qTo": 29, "price": 192.547692308}, {"qFrom": 30, "qTo": 199, "price": 192.547692308}, {"qFrom": 200, "qTo": 499, "price": 74.513846154}, {"qFrom": 500, "qTo": 999, "price": 71.895384615}, {"qFrom": 1000, "qTo": null, "price": 70.601538462}], null, null, {"Basic/Extended": {"format": "${default}", "primary": "default", "values": {"default": ["Extended", "string"]}}, "Package": {"format": "${default}", "primary": "default", "values": {"default": ["LFCSP-48", "string"]}}, "Status": {"format": "${default}", "primary": "default", "values": {"default": ["-", "string"]}}}], ["C535998", "IFX007T", 8, "Infineon Technologies", "PG-TO263-7 Pre-ordered Products RoHS", "", [{"qFrom": 1, "qTo": 9, "price": 3.743076923}, {"qFrom": 10, "qTo": 29, "price": 3.247692308}, {"qFrom": 30, "qTo": 99, "price": 3.156923077}, {"qFrom": 100, "qTo": 499, "price": 3.064615385}, {"qFrom": 500, "qTo": 999, "price": 3.024615385}, {"qFrom": 1000, "qTo": null, "price": 2.975384615}], null, null, {"Basic/Extended": {"format": "${default}", "primary": "default", "values": {"default": ["Extended", "string"]}}, "Package": {"format": "${default}", "primary": "default", "values": {"default": ["PG-TO263-7", "string"]}}, "Status": {"format": "${default}", "primary": "default", "values": {"default": ["-", "string"]}}}], ["C568216", "TOP271VG", 11, "POWER INTEGRATIONS", "eDIP-12 Pre-ordered Products RoHS", "", [{"qFrom": 1, "qTo": 9, "price": 6.289230769}, {"qFrom": 10, "qTo": 29, "price": 6.289230769}, {"qFrom": 30, "qTo": 199, "price": 6.289230769}, {"qFrom": 200, "qTo": 499, "price": 2.435384615}, {"qFrom": 500, "qTo": 999, "price": 2.349230769}, {"qFrom": 1000, "qTo": null, "price": 2.306153846}], null, null, {"Basic/Extended": {"format": "${default}", "primary": "default", "values": {"default": ["Extended", "string"]}}, "Package": {"format": "${default}", "primary": "default", "values": {"default": ["eDIP-12", "string"]}}, "Status": {"format": "${default}", "primary": "default", "values": {"default": ["-", "string"]}}}], ["C123982", "STM8S207M8T6B", 80, "STMicroelectronics", "LQFP-80_14x14x065P Pre-ordered Products RoHS", "", [{"qFrom": 1, "qTo": 9, "price": 2.509230769}, {"qFrom": 10, "qTo": 29, "price": 1.850769231}, {"qFrom": 30, "qTo": 99, "price": 1.729230769}, {"qFrom": 100, "qTo": 499, "price": 1.609230769}, {"qFrom": 500, "qTo": 999, "price": 1.555384615}, {"qFrom": 1000, "qTo": null, "price": 1.529230769}], null, null, {"Basic/Extended": {"format": "${default}", "primary": "default", "values": {"default": ["Extended", "string"]}}, "Package": {"format": "${default}", "primary": "default", "values": {"default": ["LQFP-80_14.0x14.0x0.65P", "string"]}}, "Status": {"format": "${default}", "primary": "default", "values": {"default": ["-", "string"]}}}], ["C899246", "FOD3150", 8, "ON Semiconductor", "PDIP-8 Pre-ordered Products RoHS", "", [{"qFrom": 1, "qTo": 9, "price": 0.830769231}, {"qFrom": 10, "qTo": 29, "price": 0.613846154}, {"qFrom": 30, "qTo": 99, "price": 0.573846154}, {"qFrom": 100, "qTo": 499, "price": 0.532307692}, {"qFrom": 500, "qTo": 999, "price": 0.515384615}, {"qFrom": 1000, "qTo": null, "price": 0.506153846}], null, null, {"Basic/Extended": {"format": "${default}", "primary": "default", "values": {"default": ["Extended", "string"]}}, "Package": {"format": "${default}", "primary": "default", "values": {"default": ["PDIP-8", "string"]}}, "Status": {"format": "${default}", "primary": "default", "values": {"default": ["-", "string"]}}}], ["C899248", "FOD3150AS", 8, "ON Semiconductor", "SMT-8 Pre-ordered Products RoHS", "", [{"qFrom": 1, "qTo": 9, "price": 1.872307692}, {"qFrom": 10, "qTo": 29, "price": 1.872307692}, {"qFrom": 30, "qTo": 199, "price": 1.872307692}, {"qFrom": 200, "qTo": 499, "price": 0.724615385}, {"qFrom": 500, "qTo": 999, "price": 0.7}, {"qFrom": 1000, "qTo": null, "price": 0.687692308}], null, null, {"Basic/Extended": {"format": "${default}", "primary": "default", "values": {"default": ["Extended", "string"]}}, "Package": {"format": "${default}", "primary": "default", "values": {"default": ["SMT-8", "string"]}}, "Status": {"format": "${default}", "primary": "default", "values": {"default": ["-", "string"]}}}], ["C892689", "NCP702SN18T1G", 5, "ON Semiconductor", "TSOP-5 Pre-ordered Products RoHS", "", [{"qFrom": 1, "qTo": 9, "price": 0.753846154}, {"qFrom": 10, "qTo": 29, "price": 0.753846154}, {"qFrom": 30, "qTo": 199, "price": 0.753846154}, {"qFrom": 200, "qTo": 499, "price": 0.292307692}, {"qFrom": 500, "qTo": 999, "price": 0.281538462}, {"qFrom": 1000, "qTo": null, "price": 0.276923077}], null, null, {"Basic/Extended": {"format": "${default}", "primary": "default", "values": {"default": ["Extended", "string"]}}, "Package": {"format": "${default}", "primary": "default", "values": {"default": ["TSOP-5", "string"]}}, "Status": {"format": "${default}", "primary": "default", "values": {"default": ["-", "string"]}}}], ["C894268", "SBAS40LT1G", 3, "ON Semiconductor", "SOT-23 Pre-ordered Products RoHS", "", [{"qFrom": 1, "qTo": 9, "price": 0.239076923}, {"qFrom": 10, "qTo": 29, "price": 0.239076923}, {"qFrom": 30, "qTo": 199, "price": 0.239076923}, {"qFrom": 200, "qTo": 499, "price": 0.092615385}, {"qFrom": 500, "qTo": 999, "price": 0.089230769}, {"qFrom": 1000, "qTo": null, "price": 0.087692308}], null, null, {"Basic/Extended": {"format": "${default}", "primary": "default", "values": {"default": ["Extended", "string"]}}, "Package": {"format": "${default}", "primary": "default", "values": {"default": ["SOT-23", "string"]}}, "Status": {"format": "${default}", "primary": "default", "values": {"default": ["-", "string"]}}}], ["C913862", "ISO7231MDWR", 16, "Texas Instruments", "SOIC-16 Pre-ordered Products RoHS", "", [{"qFrom": 1, "qTo": 9, "price": 6.716923077}, {"qFrom": 10, "qTo": 29, "price": 6.716923077}, {"qFrom": 30, "qTo": 199, "price": 6.716923077}, {"qFrom": 200, "qTo": 499, "price": 2.6}, {"qFrom": 500, "qTo": 999, "price": 2.509230769}, {"qFrom": 1000, "qTo": null, "price": 2.463076923}], null, null, {"Basic/Extended": {"format": "${default}", "primary": "default", "values": {"default": ["Extended", "string"]}}, "Package": {"format": "${default}", "primary": "default", "values": {"default": ["SOIC-16", "string"]}}, "Status": {"format": "${default}", "primary": "default", "values": {"default": ["-", "string"]}}}], ["C900527", "NVTFS5C478NLTAG", 11, "ON Semiconductor", "WDFN-8 Pre-ordered Products RoHS", "", [{"qFrom": 1, "qTo": 9, "price": 0.409692308}, {"qFrom": 10, "qTo": 29, "price": 0.409692308}, {"qFrom": 30, "qTo": 199, "price": 0.409692308}, {"qFrom": 200, "qTo": 499, "price": 0.158553846}, {"qFrom": 500, "qTo": 999, "price": 0.152923077}, {"qFrom": 1000, "qTo": null, "price": 0.150307692}], null, null, {"Basic/Extended": {"format": "${default}", "primary": "default", "values": {"default": ["Extended", "string"]}}, "Package": {"format": "${default}", "primary": "default", "values": {"default": ["WDFN-8", "string"]}}, "Status": {"format": "${default}", "primary": "default", "values": {"default": ["-", "string"]}}}], ["C900507", "NVTFS014P04M8LTAG", 11, "ON Semiconductor", "WDFN-8 Pre-ordered Products RoHS", "", [{"qFrom": 1, "qTo": 9, "price": 0.883076923}, {"qFrom": 10, "qTo": 29, "price": 0.883076923}, {"qFrom": 30, "qTo": 199, "price": 0.883076923}, {"qFrom": 200, "qTo": 499, "price": 0.341538462}, {"qFrom": 500, "qTo": 999, "price": 0.330769231}, {"qFrom": 1000, "qTo": null, "price": 0.324615385}], null, null, {"Basic/Extended": {"format": "${default}", "primary": "default", "values": {"default": ["Extended", "string"]}}, "Package": {"format": "${default}", "primary": "default", "values": {"default": ["WDFN-8", "string"]}}, "Status": {"format": "${default}", "primary": "default", "values": {"default": ["-", "string"]}}}], ["C1986680", "GC2000032", 2, "Diodes Incorporated", "HC-49/US Pre-ordered Products RoHS", "", [{"qFrom": 1, "qTo": 9, "price": 0.413230769}, {"qFrom": 10, "qTo": 29, "price": 0.413230769}, {"qFrom": 30, "qTo": 199, "price": 0.413230769}, {"qFrom": 200, "qTo": 499, "price": 0.159938462}, {"qFrom": 500, "qTo": 999, "price": 0.154307692}, {"qFrom": 1000, "qTo": null, "price": 0.151538462}], null, null, {"Basic/Extended": {"format": "${default}", "primary": "default", "values": {"default": ["Extended", "string"]}}, "Package": {"format": "${default}", "primary": "default", "values": {"default": ["SMD", "string"]}}, "Status": {"format": "${default}", "primary": "default", "values": {"default": ["-", "string"]}}}], ["C2450771", "ECS-120-18-36-AGM-TR", 4, "ECS", "SMD-4 Pre-ordered Products RoHS", "", [{"qFrom": 1, "qTo": 9, "price": 0.493846154}, {"qFrom": 10, "qTo": 29, "price": 0.493846154}, {"qFrom": 30, "qTo": 199, "price": 0.493846154}, {"qFrom": 200, "qTo": 499, "price": 0.192307692}, {"qFrom": 500, "qTo": 999, "price": 0.184615385}, {"qFrom": 1000, "qTo": null, "price": 0.181538462}], null, null, {"Basic/Extended": {"format": "${default}", "primary": "default", "values": {"default": ["Extended", "string"]}}, "Package": {"format": "${default}", "primary": "default", "values": {"default": ["SMD-4", "string"]}}, "Status": {"format": "${default}", "primary": "default", "values": {"default": ["-", "string"]}}}], ["C570466", "FI-RE51S-HF-R1500", 61, "JAE Electronics", "Pre-ordered Products RoHS", "", [{"qFrom": 1, "qTo": 9, "price": 6.173846154}, {"qFrom": 10, "qTo": 29, "price": 6.173846154}, {"qFrom": 30, "qTo": 199, "price": 6.173846154}, {"qFrom": 200, "qTo": 499, "price": 2.389230769}, {"qFrom": 500, "qTo": 999, "price": 2.306153846}, {"qFrom": 1000, "qTo": null, "price": 2.264615385}], null, null, {"Basic/Extended": {"format": "${default}", "primary": "default", "values": {"default": ["Extended", "string"]}}, "Package": {"format": "${default}", "primary": "default", "values": {"default": ["FPC", "string"]}}, "Status": {"format": "${default}", "primary": "default", "values": {"default": ["-", "string"]}}}], ["C890982", "FDMD8260LET60", 14, "ON Semiconductor", "PQFN-12 Pre-ordered Products RoHS", "", [{"qFrom": 1, "qTo": 9, "price": 4.366153846}, {"qFrom": 10, "qTo": 29, "price": 4.366153846}, {"qFrom": 30, "qTo": 199, "price": 4.366153846}, {"qFrom": 200, "qTo": 499, "price": 1.690769231}, {"qFrom": 500, "qTo": 999, "price": 1.630769231}, {"qFrom": 1000, "qTo": null, "price": 1.601538462}], null, null, {"Basic/Extended": {"format": "${default}", "primary": "default", "values": {"default": ["Extended", "string"]}}, "Package": {"format": "${default}", "primary": "default", "values": {"default": ["PQFN-12", "string"]}}, "Status": {"format": "${default}", "primary": "default", "values": {"default": ["-", "string"]}}}], ["C913808", "D-DMSC25PM-F001", 27, "Ckmtw(Shenzhen Cankemeng)", "Pre-ordered Products RoHS", "", [{"qFrom": 1, "qTo": 9, "price": 2.327692308}, {"qFrom": 10, "qTo": 29, "price": 1.712307692}, {"qFrom": 30, "qTo": 99, "price": 1.6}, {"qFrom": 100, "qTo": 499, "price": 1.486153846}, {"qFrom": 500, "qTo": 999, "price": 1.436923077}, {"qFrom": 1000, "qTo": null, "price": 1.412307692}], null, null, {"Basic/Extended": {"format": "${default}", "primary": "default", "values": {"default": ["Extended", "string"]}}, "Package": {"format": "${default}", "primary": "default", "values": {"default": ["Through Hole", "string"]}}, "Status": {"format": "${default}", "primary": "default", "values": {"default": ["-", "string"]}}}], ["C890981", "FDMD8260L", 14, "ON Semiconductor", "PQFN-12 Pre-ordered Products RoHS", "", [{"qFrom": 1, "qTo": 9, "price": 3.969230769}, {"qFrom": 10, "qTo": 29, "price": 3.969230769}, {"qFrom": 30, "qTo": 199, "price": 3.969230769}, {"qFrom": 200, "qTo": 499, "price": 1.536923077}, {"qFrom": 500, "qTo": 999, "price": 1.483076923}, {"qFrom": 1000, "qTo": null, "price": 1.455384615}], null, null, {"Basic/Extended": {"format": "${default}", "primary": "default", "values": {"default": ["Extended", "string"]}}, "Package": {"format": "${default}", "primary": "default", "values": {"default": ["PQFN-12", "string"]}}, "Status": {"format": "${default}", "primary": "default", "values": {"default": ["-", "string"]}}}], ["C2687661", "ESE58L11B", 2, "PANASONIC", "Pre-ordered Products RoHS", "", [{"qFrom": 1, "qTo": 9, "price": 0.470769231}, {"qFrom": 10, "qTo": 29, "price": 0.470769231}, {"qFrom": 30, "qTo": 199, "price": 0.470769231}, {"qFrom": 200, "qTo": 499, "price": 0.183076923}, {"qFrom": 500, "qTo": 999, "price": 0.175384615}, {"qFrom": 1000, "qTo": null, "price": 0.172307692}], null, null, {"Basic/Extended": {"format": "${default}", "primary": "default", "values": {"default": ["Extended", "string"]}}, "Package": {"format": "${default}", "primary": "default", "values": {"default": ["SMD", "string"]}}, "Status": {"format": "${default}", "primary": "default", "values": {"default": ["-", "string"]}}}], ["C1986193", "FW520WFMT1", 4, "Diodes Incorporated", "SMD-4 Pre-ordered Products RoHS", "", [{"qFrom": 1, "qTo": 9, "price": 0.938461538}, {"qFrom": 10, "qTo": 29, "price": 0.938461538}, {"qFrom": 30, "qTo": 199, "price": 0.938461538}, {"qFrom": 200, "qTo": 499, "price": 0.363076923}, {"qFrom": 500, "qTo": 999, "price": 0.350769231}, {"qFrom": 1000, "qTo": null, "price": 0.344615385}], null, null, {"Basic/Extended": {"format": "${default}", "primary": "default", "values": {"default": ["Extended", "string"]}}, "Package": {"format": "${default}", "primary": "default", "values": {"default": ["SMD-4", "string"]}}, "Status": {"format": "${default}", "primary": "default", "values": {"default": ["-", "string"]}}}], ["C906812", "MC10H116DG", 16, "ON Semiconductor", "SOIC-Narrow-16 Pre-ordered Products RoHS", "", [{"qFrom": 1, "qTo": 9, "price": 7.029230769}, {"qFrom": 10, "qTo": 29, "price": 7.029230769}, {"qFrom": 30, "qTo": 199, "price": 7.029230769}, {"qFrom": 200, "qTo": 499, "price": 2.72}, {"qFrom": 500, "qTo": 999, "price": 2.624615385}, {"qFrom": 1000, "qTo": null, "price": 2.576923077}], null, null, {"Basic/Extended": {"format": "${default}", "primary": "default", "values": {"default": ["Extended", "string"]}}, "Package": {"format": "${default}", "primary": "default", "values": {"default": ["SOIC-Narrow-16", "string"]}}, "Status": {"format": "${default}", "primary": "default", "values": {"default": ["-", "string"]}}}], ["C894582", "SZMMBZ5227BLT1G", 3, "ON Semiconductor", "SOT-23-3 Pre-ordered Products RoHS", "", [{"qFrom": 1, "qTo": 9, "price": 0.044923077}, {"qFrom": 10, "qTo": 29, "price": 0.044923077}, {"qFrom": 30, "qTo": 199, "price": 0.044923077}, {"qFrom": 200, "qTo": 499, "price": 0.017384615}, {"qFrom": 500, "qTo": 999, "price": 0.016769231}, {"qFrom": 1000, "qTo": null, "price": 0.016461538}], null, null, {"Basic/Extended": {"format": "${default}", "primary": "default", "values": {"default": ["Extended", "string"]}}, "Package": {"format": "${default}", "primary": "default", "values": {"default": ["SOT-23-3", "string"]}}, "Status": {"format": "${default}", "primary": "default", "values": {"default": ["-", "string"]}}}], ["C890607", "EMI4193MTTAG", 14, "ON Semiconductor", "WDFN-16 Pre-ordered Products RoHS", "", [{"qFrom": 1, "qTo": 9, "price": 1.141538462}, {"qFrom": 10, "qTo": 29, "price": 1.141538462}, {"qFrom": 30, "qTo": 199, "price": 1.141538462}, {"qFrom": 200, "qTo": 499, "price": 0.443076923}, {"qFrom": 500, "qTo": 999, "price": 0.426153846}, {"qFrom": 1000, "qTo": null, "price": 0.418461538}], null, null, {"Basic/Extended": {"format": "${default}", "primary": "default", "values": {"default": ["Extended", "string"]}}, "Package": {"format": "${default}", "primary": "default", "values": {"default": ["WDFN-16", "string"]}}, "Status": {"format": "${default}", "primary": "default", "values": {"default": ["-", "string"]}}}], ["C913851", "LMZ23605TZX/NOPB", 8, "Texas Instruments", "TO-PMOD-7 Pre-ordered Products RoHS", "", [{"qFrom": 1, "qTo": 9, "price": 27.347692308}, {"qFrom": 10, "qTo": 29, "price": 27.347692308}, {"qFrom": 30, "qTo": 199, "price": 27.347692308}, {"qFrom": 200, "qTo": 499, "price": 10.584615385}, {"qFrom": 500, "qTo": 999, "price": 10.212307692}, {"qFrom": 1000, "qTo": null, "price": 10.027692308}], null, null, {"Basic/Extended": {"format": "${default}", "primary": "default", "values": {"default": ["Extended", "string"]}}, "Package": {"format": "${default}", "primary": "default", "values": {"default": ["TO-PMOD-7", "string"]}}, "Status": {"format": "${default}", "primary": "default", "values": {"default": ["-", "string"]}}}], ["C2762328", "1206CG200J202NT", 2, "FH(Guangdong Fenghua Advanced Tech)", "1206(3216) Pre-ordered Products RoHS", "", [{"qFrom": 1, "qTo": 9, "price": 0.087692308}, {"qFrom": 10, "qTo": 29, "price": 0.087692308}, {"qFrom": 30, "qTo": 199, "price": 0.087692308}, {"qFrom": 200, "qTo": 499, "price": 0.034}, {"qFrom": 500, "qTo": 999, "price": 0.032769231}, {"qFrom": 1000, "qTo": null, "price": 0.032153846}], null, null, {"Basic/Extended": {"format": "${default}", "primary": "default", "values": {"default": ["Extended", "string"]}}, "Package": {"format": "${default}", "primary": "default", "values": {"default": ["1206", "string"]}}, "Status": {"format": "${default}", "primary": "default", "values": {"default": ["-", "string"]}}}]], "category": "Hardwares & Others", "subcategory": "Pre-ordered Products"}